Metadata-Version: 1.0
Name: distributionsalnew
Version: 0.1
Summary: Gaussian distributions
Home-page: UNKNOWN
Author: Raghuraj
Author-email: UNKNOWN
License: UNKNOWN
Platform: UNKNOWN
